zepben/python-lib-test/__init__.py
zepben.test_ci_central-0.33.0b2.dist-info/LICENSE
zepben.test_ci_central-0.33.0b2.dist-info/METADATA
zepben.test_ci_central-0.33.0b2.dist-info/WHEEL
zepben.test_ci_central-0.33.0b2.dist-info/top_level.txt
zepben.test_ci_central-0.33.0b2.dist-info/RECORD
